httpie_astra.py
httpie_astra-0.1.3.dist-info/LICENSE
httpie_astra-0.1.3.dist-info/METADATA
httpie_astra-0.1.3.dist-info/WHEEL
httpie_astra-0.1.3.dist-info/entry_points.txt
httpie_astra-0.1.3.dist-info/top_level.txt
httpie_astra-0.1.3.dist-info/RECORD
