Metadata-Version: 2.1
Name: httpie-astra
Version: 0.1.3
Summary: Astra plugin for HTTPie.
Home-page: https://github.com/synedra-datastax/httpie-astra
Download-URL: https://github.com/synedra-datastax/httpie-astra
Author: Kirsten Hunter
Author-email: kirsten.hunter@datastax.com
License: Apache 2.0
Requires-Python: >=3.3
License-File: LICENSE
Requires-Dist: httpie (>=3.2.1)
